pytree/__init__.py
pytree/main.py
directory_pytree-0.1.0.dist-info/METADATA
directory_pytree-0.1.0.dist-info/WHEEL
directory_pytree-0.1.0.dist-info/entry_points.txt
directory_pytree-0.1.0.dist-info/top_level.txt
directory_pytree-0.1.0.dist-info/RECORD
