Metadata-Version: 2.1
Name: directory-pytree
Version: 0.1.0
Summary: A simple directory tree display tool
Author-email: 陈定钢 <945036663@qq.com>
Requires-Python: >=3.6
